LICENSE
MANIFEST.in
README.md
setup.cfg
setup.py
a3kazoo/__init__.py
a3kazoo/utils.py
a3kazoo.egg-info/PKG-INFO
a3kazoo.egg-info/SOURCES.txt
a3kazoo.egg-info/dependency_links.txt
a3kazoo.egg-info/not-zip-safe
a3kazoo.egg-info/requires.txt
a3kazoo.egg-info/top_level.txt
a3kazoo/scene_cases/__init__.py
a3kazoo/scene_cases/watch_nodes/__init__.py
a3kazoo/scene_cases/watch_nodes/abstract_node_change_service.py
a3kazoo/scene_cases/watch_nodes/cmds.py
a3kazoo/scene_cases/watch_nodes/node_thread.py